stockquotes/__init__.py
stockquotes/script.py
stockquotes-1.0.5.dist-info/LICENSE
stockquotes-1.0.5.dist-info/METADATA
stockquotes-1.0.5.dist-info/WHEEL
stockquotes-1.0.5.dist-info/top_level.txt
stockquotes-1.0.5.dist-info/RECORD
