Metadata-Version: 2.1
Name: stockquotes
Version: 1.0.5
Summary: A simple module for retreiving stock data
Home-page: UNKNOWN
License: UNKNOWN
Platform: UNKNOWN
Classifier: Programming Language :: Python :: 3
Classifier: Operating System :: OS Independent
Requires-Python: >=3.0
